xlsxwriter_tables/__init__.py
xlsxwriter_tables/xlsxwriter_tables.py
xlsxwriter_tables-0.0.1.dist-info/LICENSE
xlsxwriter_tables-0.0.1.dist-info/METADATA
xlsxwriter_tables-0.0.1.dist-info/WHEEL
xlsxwriter_tables-0.0.1.dist-info/top_level.txt
xlsxwriter_tables-0.0.1.dist-info/RECORD
