Metadata-Version: 2.1
Name: xlsxwriter-tables
Version: 0.0.1
Summary: Easily export nested data to Excel
Home-page: https://github.com/johncmacy/xlsxwriter-tables/
Author: John Macy
Author-email: johncmacy@gmail.com
License: UNKNOWN
Platform: UNKNOWN
Classifier: Programming Language :: Python :: 3.9
Classifier: License :: OSI Approved :: MIT License
